LICENSE
MANIFEST.in
VERSION
setup.cfg
setup.py
flowdas.H.egg-info/PKG-INFO
flowdas.H.egg-info/SOURCES.txt
flowdas.H.egg-info/dependency_links.txt
flowdas.H.egg-info/entry_points.txt
flowdas.H.egg-info/requires.txt
flowdas.H.egg-info/top_level.txt
flowdas.H.egg-info/zip-safe
flowdas/boot/__init__.py
flowdas/boot/command.py
flowdas/boot/config.py
flowdas/boot/main.py
flowdas/boot/testing.py
flowdas/function/__init__.py
flowdas/function/_function.py
flowdas/http/__init__.py
flowdas/http/asgi.py
flowdas/http/auth.py
flowdas/http/boot.py
flowdas/http/route.py
flowdas/jsonrpc/__init__.py
flowdas/jsonrpc/openrpc.py
flowdas/runner/__init__.py
flowdas/runner/boot.py
flowdas/runner/pidfile.py
flowdas/runner/server.py
typeable/__init__.py
typeable/_cast.py
typeable/_constraint.py
typeable/_context.py
typeable/_json.py
typeable/_object.py
typeable/typing.py